yopass_api/__init__.py
yopass_api/yopass_api.py
yopass_api-0.0.8.dist-info/LICENSE
yopass_api-0.0.8.dist-info/METADATA
yopass_api-0.0.8.dist-info/WHEEL
yopass_api-0.0.8.dist-info/RECORD
