Metadata-Version: 2.1
Name: yopass-api
Version: 0.0.8
Summary: This module will allow you to use Python and Yopass in automation projects
Home-page: https://github.com/silyashevich/yopass_api
License: MIT
Keywords: api,cryptography,yopass
Author: Sergey Ilyashevich
Author-email: silyashevich@gmail.com
Maintainer: Sergey Ilyashevich
Maintainer-email: silyashevich@gmail.com
Requires-Python: >=3.7,<4.0
Classifier: License :: OSI Approved :: MIT License
Classifier: Operating System :: OS Independent
Classifier: Programming Language :: Python :: 3
Classifier: Programming Language :: Python :: 3.7
Classifier: Programming Language :: Python :: 3.8
Classifier: Programming Language :: Python :: 3.9
Classifier: Programming Language :: Python :: 3.10
Classifier: Programming Language :: Python :: 3.11
Classifier: Programming Language :: Python :: 3.10
Classifier: Topic :: Security :: Cryptography
Requires-Dist: pgpy (>=0.6.0,<0.7.0)
Requires-Dist: requests (>=2.28.2,<3.0.0)
Project-URL: Repository, https://github.com/silyashevich/yopass_api
